pyfs_application/__init__.py
pyfs_application/application.py
pyfs_application-1.0.2.dist-info/METADATA
pyfs_application-1.0.2.dist-info/WHEEL
pyfs_application-1.0.2.dist-info/top_level.txt
pyfs_application-1.0.2.dist-info/RECORD
